examples/ham.sv
/* ham.sv
 * A quick and dirty Hamming encoding bit vector corrector module. Used as a
 * part of an 18341 homework, which we will use as an example input to the sv2v
 * testing suite.
 *
 * This code is property of Carnegie Mellon University's 18341 course.
 *
 * Author: Edric Kusuma
 *****************************************************************************/
`default_nettype none

module hamFix(
    input logic clock,          // posedge
    input logic [15:1] ham,     // 15-bit hamming encoding bit vector
    output logic [15:1] fixed); // the corrected bit vector

    logic [15:1] fixedAsync;
    logic p1, p2, p4, p8;
    logic [3:0] syndrome;
    assign p1 = ham[1];
    assign p2 = ham[2];
    assign p4 = ham[4];
    assign p8 = ham[8];
    assign syndrome = {p8, p4, p2, p1};

    always_comb begin
        fixedAsync = ham;
        if (syndrome != 4'b0000)                  // Errors to fix
            fixedAsync[syndrome] = ~ham[syndrome];  // Flip bit
    end

    always_ff @(posedge clock)
        fixed <= fixedAsync;

endmodule: hamFix

examples/ham_tb.sv
/* ham_tb.sv
 * The testbench for the hamFix module. Can be used to verify the behavior of
 * both the SystemVerilog and Verilog descriptions. Because this TB is written
 * in SystemVerilog, it will have to be compiled as such (i.e. using the
 * `-sverilog` flag in VCS).
 *
 * This code is property of Carnegie Mellon University's 18341 course.
 *
 * Author: Edric Kusuma
 *****************************************************************************/
`default_nettype none

module hamFix_test;
    logic clock, hasErrors;
    logic [15:1] ham, fixed, enc;
    logic [12:1] i;

    hamFix DUT(.*);

    initial begin
        clock = 0;
        forever #5 clock = ~clock;
    end

    function logic [15:1] hamEncode(
        input logic [11:1] data
    );
        logic p1, p2, p4, p8;
        logic [15:1] encoded;

        p1 = data[1] ^ data[2] ^ data[4] ^ data[5] ^ data[7] ^
             data[9] ^ data[11];
        p2 = data[1] ^ data[3] ^ data[4] ^ data[6] ^ data[7] ^
             data[10] ^ data[11];
        p4 = data[2] ^ data[3] ^ data[4] ^ data[8] ^ data[9] ^
             data[10] ^ data[11];
        p8 = data[5] ^ data[6] ^ data[7] ^ data[8] ^ data[9] ^
             data[10] ^ data[11];

        encoded[1] = p1;
        encoded[2] = p2;
        encoded[3] = data[1];
        encoded[4] = p4;
        encoded[5] = data[2];
        encoded[6] = data[3];
        encoded[7] = data[4];
        encoded[8] = p8;
        encoded[9] = data[5];
        encoded[10] = data[6];
        encoded[11] = data[7];
        encoded[12] = data[8];
        encoded[13] = data[9];
        encoded[14] = data[10];
        encoded[15] = data[11];

        return encoded;

    endfunction

    function logic [15:1] hamDecode (
        input logic [15:1] ham
    );
        logic [15:1] fixed;
        logic [3:0] syndrome;
        logic p1, p2, p4, p8;
        p1 = ham[1];
        p2 = ham[2];
        p4 = ham[4];
        p8 = ham[8];
        syndrome = {p8, p4, p2, p1};

        fixed = ham;
        if (syndrome != 4'b0000)
            fixed[syndrome] = ~ham[syndrome];

        return fixed;

    endfunction

    initial begin
        hasErrors = 0;
        @(posedge clock);
        for (i = 12'd0; i < 12'b1000_0000_0000; i++) begin
            enc = hamEncode(i[11:1]);
            ham <= enc;
            @(posedge clock);
            // Delay of 1 to allow signals to settle
            #1 assert (fixed == hamDecode(enc)) else begin
                $error("Error: expected(%b) actual(%b) for input(%b)",
                    hamDecode(enc), fixed, enc);
                hasErrors = 1;
            end
        end

        @(posedge clock);
        if (!hasErrors)
            $display("All tests passed!");
        #10 $finish;
    end

endmodule: hamFix_test

examples/good.vcd
$date
	Tue May 14 14:23:56 2019
$end

$version
	Synopsys VCS version K-2015.09_Full64
$end

$timescale
	1s
$end

$comment Csum: 1 a573cb53cd8c1e63 $end


$scope module hamFix_test $end
$var reg 1 ! clock $end
$var reg 1 " hasErrors $end
$var reg 15 # ham [15:1] $end
$var reg 15 $ fixed [15:1] $end
$var reg 15 % enc [15:1] $end
$var reg 12 & i [12:1] $end

$scope function hamEncode $end
$var reg 15 ' hamEncode [15:1] $end
$var reg 11 ( data [11:1] $end
$var reg 1 ) p1 $end
$var reg 1 * p2 $end
$var reg 1 + p4 $end
$var reg 1 , p8 $end
$var reg 15 - encoded [15:1] $end
$upscope $end


$scope function hamDecode $end
$var reg 15 . hamDecode [15:1] $end
$var reg 15 / ham [15:1] $end
$var reg 15 0 fixed [15:1] $end
$var reg 4 1 syndrome [3:0] $end
$var reg 1 2 p1 $end
$var reg 1 3 p2 $end
$var reg 1 4 p4 $end
$var reg 1 5 p8 $end
$upscope $end


$scope module DUT $end
$var reg 1 ! clock $end
$var reg 15 # ham [15:1] $end
$var reg 15 $ fixed [15:1] $end
$var reg 15 6 fixedAsync [15:1] $end
$var reg 1 7 p1 $end
$var reg 1 8 p2 $end
$var reg 1 9 p4 $end
$var reg 1 : p8 $end
$var reg 4 ; syndrome [3:0] $end
$upscope $end

$upscope $end

$enddefinitions $end

#0
$dumpvars
x7
x8
x9
x:
0!
x2
x3
x4
x5
x)
x*
x+
x,
0"
bxxxx ;
bxxxxxxxxxxxxxxx %
bxxxxxxxxxxxxxxx $
bxxxxxxxxxxxxxxx 6
bxxxxxxxxxxxxxxx #
bxxxxxxxxxxxxxxx 0
bxxxxxxxxxxxxxxx /
bxxxxxxxxxxxxxxx .
bxxxx 1
bxxxxxxxxxxx (
bxxxxxxxxxxxxxxx -
bxxxxxxxxxxxxxxx '
bxxxxxxxxxxxx &
$end
#5
1!
b000000000000 &
b00000000000 (
0)
0*
0+
0,
b000000000000000 -
b000000000000000 '
b000000000000000 %
b000000000000000 #
07
08
09
0:
b000000000000000 6
b0000 ;
#10
0!
#15
1!
b000000000000000 $
#16
b000000000000000 /
02
03
04
05
b0000 1
b000000000000000 0
b000000000000000 .
b000000000001 &
b00000000001 (
1)
1*
b000000000000111 -
b000000000000111 '
b000000000000111 %
b000000000000111 #
17
18
b000000000000111 6
b0011 ;
b000000000000011 6
#20
0!
#25
1!
b000000000000011 $
#26
b000000000000111 /
12
13
b0011 1
b000000000000011 0
b000000000000011 .
b000000000010 &
b00000000010 (
0*
1+
b000000000011001 -
b000000000011001 '
b000000000011001 %
b000000000011001 #
08
19
b000000000011101 6
b0101 ;
b000000000001001 6
#30
0!
#35
1!
b000000000001001 $
#36
b000000000011001 /
03
14
b0101 1
b000000000001001 0
b000000000001001 .
b000000000011 &
b00000000011 (
0)
1*
b000000000011110 -
b000000000011110 '
b000000000011110 %
b000000000011110 #
07
18
b000000000001110 6
b0110 ;
b000000000111110 6
#40
0!
#45
1!
b000000000111110 $
#46
b000000000011110 /
02
13
b0110 1
b000000000111110 0
b000000000111110 .
b000000000100 &
b00000000100 (
b000000000101010 -
b000000000101010 '
b000000000101010 %
b000000000101010 #
b000000000001010 6
#50
0!
#55
1!
b000000000001010 $
#56
b000000000101010 /
b000000000001010 0
b000000000001010 .
b000000000101 &
b00000000101 (
1)
0*
b000000000101101 -
b000000000101101 '
b000000000101101 %
b000000000101101 #
17
08
b000000000001101 6
b0101 ;
b000000000111101 6
#60
0!
#65
1!
b000000000111101 $
#66
b000000000101101 /
12
03
b0101 1
b000000000111101 0
b000000000111101 .
b000000000110 &
b00000000110 (
1*
0+
b000000000110011 -
b000000000110011 '
b000000000110011 %
b000000000110011 #
18
09
b000000000100011 6
b0011 ;
b000000000110111 6
#70
0!
#75
1!
b000000000110111 $
#76
b000000000110011 /
13
04
b0011 1
b000000000110111 0
b000000000110111 .
b000000000111 &
b00000000111 (
0)
0*
b000000000110100 -
b000000000110100 '
b000000000110100 %
b000000000110100 #
07
08
b000000000110000 6
b0000 ;
b000000000110100 6
#80
0!
#85
1!
b000000000110100 $
#86
b000000000110100 /
02
03
b0000 1
b000000000110100 0
b000000000110100 .
b000000001000 &
b00000001000 (
1)
1*
1+
b000000001001011 -
b000000001001011 '
b000000001001011 %
b000000001001011 #
17
18
19
b000000001001011 6
b0111 ;
b000000000001011 6
#90
0!
#95
1!
b000000000001011 $
#96
b000000001001011 /
12
13
14
b0111 1
b000000000001011 0
b000000000001011 .
b000000001001 &
b00000001001 (
0)
0*
b000000001001100 -
b000000001001100 '
b000000001001100 %
b000000001001100 #
07
08
b000000000001100 6
b0100 ;
b000000001000100 6
#100
0!
#105
1!
b000000001000100 $
#106
b000000001001100 /
02
03
b0100 1
b000000001000100 0
b000000001000100 .
b000000001010 &
b00000001010 (
1*
0+
b000000001010010 -
b000000001010010 '
b000000001010010 %
b000000001010010 #
18
09
b000000001011010 6
b0010 ;
b000000001010000 6
#110
0!
#115
1!
b000000001010000 $
#116
b000000001010010 /
13
04
b0010 1
b000000001010000 0
b000000001010000 .
b000000001011 &
b00000001011 (
1)
0*
b000000001010101 -
b000000001010101 '
b000000001010101 %
b000000001010101 #
17
08
b000000001010111 6
b0001 ;
b000000001010100 6
#120
0!
#125
1!
b000000001010100 $
#126
b000000001010101 /
12
03
b0001 1
b000000001010100 0
b000000001010100 .
b000000001100 &
b00000001100 (
b000000001100001 -
b000000001100001 '
b000000001100001 %
b000000001100001 #
b000000001100000 6
#130
0!
#135
1!
b000000001100000 $
#136
b000000001100001 /
b000000001100000 0
b000000001100000 .
b000000001101 &
b00000001101 (
0)
1*
b000000001100110 -
b000000001100110 '
b000000001100110 %
b000000001100110 #
07
18
b000000001100111 6
b0010 ;
b000000001100100 6
#140
0!
#145
1!
b000000001100100 $
#146
b000000001100110 /
02
13
b0010 1
b000000001100100 0
b000000001100100 .
b000000001110 &
b00000001110 (
0*
1+
b000000001111000 -
b000000001111000 '
b000000001111000 %
b000000001111000 #
08
19
b000000001111010 6
b0100 ;
b000000001110000 6
#150
0!
#155
1!
b000000001110000 $
#156
b000000001111000 /
03
14
b0100 1
b000000001110000 0
b000000001110000 .
b000000001111 &
b00000001111 (
1)
1*
b000000001111111 -
b000000001111111 '
b000000001111111 %
b000000001111111 #
17
18
b000000001110111 6
b0111 ;
b000000000111111 6
#160
0!
#165
1!
b000000000111111 $
#166
b000000001111111 /
12
13
b0111 1
b000000000111111 0
b000000000111111 .
b000000010000 &
b00000010000 (
0*
0+
1,
b000000110000001 -
b000000110000001 '
b000000110000001 %
b000000110000001 #
08
09
1:
b000000111000001 6
b1001 ;
b000000010000001 6
#170
0!
#175
1!
b000000010000001 $
#176
b000000110000001 /
03
04
15
b1001 1
b000000010000001 0
b000000010000001 .
b000000010001 &
b00000010001 (
0)
1*
b000000110000110 -
b000000110000110 '
b000000110000110 %
b000000110000110 #
07
18
b000000010000110 6
b1010 ;
b000001110000110 6
#180
0!
#185
1!
b000001110000110 $
#186
b000000110000110 /
02
13
b1010 1
b000001110000110 0
b000001110000110 .
b000000010010 &
b00000010010 (
0*
1+
b000000110011000 -
b000000110011000 '
b000000110011000 %
b000000110011000 #
08
19
b000001110011000 6
b1100 ;
b000100110011000 6
#190
0!
#195
1!
b000100110011000 $
#196
b000000110011000 /
03
14
b1100 1
b000100110011000 0
b000100110011000 .
b000000010011 &
b00000010011 (
1)
1*
b000000110011111 -
b000000110011111 '
b000000110011111 %
b000000110011111 #
17
18
b000100110011111 6
b1111 ;
b100000110011111 6
#200
0!
#205
1!
b100000110011111 $
#206
b000000110011111 /
12
13
b1111 1
b100000110011111 0
b100000110011111 .
b000000010100 &
b00000010100 (
b000000110101011 -
b000000110101011 '
b000000110101011 %
b000000110101011 #
b100000110101011 6
#210
0!
#215
1!
b100000110101011 $
#216
b000000110101011 /
b100000110101011 0
b100000110101011 .
b000000010101 &
b00000010101 (
0)
0*
b000000110101100 -
b000000110101100 '
b000000110101100 %
b000000110101100 #
07
08
b100000110101100 6
b1100 ;
b000100110101100 6
#220
0!
#225
1!
b000100110101100 $
#226
b000000110101100 /
02
03
b1100 1
b000100110101100 0
b000100110101100 .
b000000010110 &
b00000010110 (
1*
0+
b000000110110010 -
b000000110110010 '
b000000110110010 %
b000000110110010 #
18
09
b000100110110010 6
b1010 ;
b000001110110010 6
#230
0!
#235
1!
b000001110110010 $
#236
b000000110110010 /
13
04
b1010 1
b000001110110010 0
b000001110110010 .
b000000010111 &
b00000010111 (
1)
0*
b000000110110101 -
b000000110110101 '
b000000110110101 %
b000000110110101 #
17
08
b000001110110101 6
b1001 ;
b000000010110101 6
#240
0!
#245
1!
b000000010110101 $
#246
b000000110110101 /
12
03
b1001 1
b000000010110101 0
b000000010110101 .
b000000011000 &
b00000011000 (
0)
1*
1+
b000000111001010 -
b000000111001010 '
b000000111001010 %
b000000111001010 #
07
18
19
b000000011001010 6
b1110 ;
b010000111001010 6
#250
0!
#255
1!
b010000111001010 $
#256
b000000111001010 /
02
13
14
b1110 1
b010000111001010 0
b010000111001010 .
b000000011001 &
b00000011001 (
1)
0*
b000000111001101 -
b000000111001101 '
b000000111001101 %
b000000111001101 #
17
08
b010000111001101 6
b1101 ;
b001000111001101 6
#260
0!
#265
1!
b001000111001101 $
#266
b000000111001101 /
12
03
b1101 1
b001000111001101 0
b001000111001101 .
b000000011010 &
b00000011010 (
1*
0+
b000000111010011 -
b000000111010011 '
b000000111010011 %
b000000111010011 #
18
09
b001000111010011 6
b1011 ;
b000010111010011 6
#270
0!
#275
1!
b000010111010011 $
#276
b000000111010011 /
13
04
b1011 1
b000010111010011 0
b000010111010011 .
b000000011011 &
b00000011011 (
0)
0*
b000000111010100 -
b000000111010100 '
b000000111010100 %
b000000111010100 #
07
08
b000010111010100 6
b1000 ;
b000000101010100 6
#280
0!
#285
1!
b000000101010100 $
#286
b000000111010100 /
02
03
b1000 1
b000000101010100 0
b000000101010100 .
b000000011100 &
b00000011100 (
b000000111100000 -
b000000111100000 '
b000000111100000 %
b000000111100000 #
b000000101100000 6
#290
0!
#295
1!
b000000101100000 $
#296
b000000111100000 /
b000000101100000 0
b000000101100000 .
b000000011101 &
b00000011101 (
1)
1*
b000000111100111 -
b000000111100111 '
b000000111100111 %
b000000111100111 #
17
18
b000000101100111 6
b1011 ;
b000010111100111 6
#300
0!
#305
1!
b000010111100111 $
#306
b000000111100111 /
12
13
b1011 1
b000010111100111 0
b000010111100111 .
b000000011110 &
b00000011110 (
0*
1+
b000000111111001 -
b000000111111001 '
b000000111111001 %
b000000111111001 #
08
19
b000010111111001 6
b1101 ;
b001000111111001 6
#310
0!
#315
1!
b001000111111001 $
#316
b000000111111001 /
03
14
b1101 1
b001000111111001 0
b001000111111001 .
b000000011111 &
b00000011111 (
0)
1*
b000000111111110 -
b000000111111110 '
b000000111111110 %
b000000111111110 #
07
18
b001000111111110 6
b1110 ;
b010000111111110 6
#320
0!
#325
1!
b010000111111110 $
#326
b000000111111110 /
02
13
b1110 1
b010000111111110 0
b010000111111110 .
b000000100000 &
b00000100000 (
0+
b000001010000010 -
b000001010000010 '
b000001010000010 %
b000001010000010 #
09
b010001010000010 6
b1010 ;
b000000010000010 6
#330
0!
#335
1!
b000000010000010 $
#336
b000001010000010 /
04
b1010 1
b000000010000010 0
b000000010000010 .
b000000100001 &
b00000100001 (
1)
0*
b000001010000101 -
b000001010000101 '
b000001010000101 %
b000001010000101 #
17
08
b000000010000101 6
b1001 ;
b000001110000101 6
#340
0!
#345
1!
b000001110000101 $
#346
b000001010000101 /
12
03
b1001 1
b000001110000101 0
b000001110000101 .
b000000100010 &
b00000100010 (
1*
1+
b000001010011011 -
b000001010011011 '
b000001010011011 %
b000001010011011 #
18
19
b000001110011011 6
b1111 ;
b100001010011011 6
#350
0!
#355
1!
b100001010011011 $
#356
b000001010011011 /
13
14
b1111 1
b100001010011011 0
b100001010011011 .
b000000100011 &
b00000100011 (
0)
0*
b000001010011100 -
b000001010011100 '
b000001010011100 %
b000001010011100 #
07
08
b100001010011100 6
b1100 ;
b000101010011100 6
#360
0!
#365
1!
b000101010011100 $
#366
b000001010011100 /
02
03
b1100 1
b000101010011100 0
b000101010011100 .
b000000100100 &
b00000100100 (
b000001010101000 -
b000001010101000 '
b000001010101000 %
b000001010101000 #
b000101010101000 6
#370
0!
#375
1!
b000101010101000 $
#376
b000001010101000 /
b000101010101000 0
b000101010101000 .
b000000100101 &
b00000100101 (
1)
1*
b000001010101111 -
b000001010101111 '
b000001010101111 %
b000001010101111 #
17
18
b000101010101111 6
b1111 ;
b100001010101111 6
#380
0!
#385
1!
b100001010101111 $
#386
b000001010101111 /
12
13
b1111 1
b100001010101111 0
b100001010101111 .
b000000100110 &
b00000100110 (
0*
0+
b000001010110001 -
b000001010110001 '
b000001010110001 %
b000001010110001 #
08
09
b100001010110001 6
b1001 ;
b000001110110001 6
#390
0!
#395
1!
b000001110110001 $
#396
b000001010110001 /
03
04
b1001 1
b000001110110001 0
b000001110110001 .
b000000100111 &
b00000100111 (
0)
1*
b000001010110110 -
b000001010110110 '
b000001010110110 %
b000001010110110 #
07
18
b000001110110110 6
b1010 ;
b000000010110110 6
#400
0!
#405
1!
b000000010110110 $
#406
b000001010110110 /
02
13
b1010 1
b000000010110110 0
b000000010110110 .
b000000101000 &
b00000101000 (
1)
0*
1+
b000001011001001 -
b000001011001001 '
b000001011001001 %
b000001011001001 #
17
08
19
b000000011001001 6
b1101 ;
b001001011001001 6
#410
0!
#415
1!
b001001011001001 $
#416
b000001011001001 /
12
03
14
b1101 1
b001001011001001 0
b001001011001001 .
b000000101001 &
b00000101001 (
0)
1*
b000001011001110 -
b000001011001110 '
b000001011001110 %
b000001011001110 #
07
18
b001001011001110 6
b1110 ;
b010001011001110 6
#420
0!
#425
1!
b010001011001110 $
#426
b000001011001110 /
02
13
b1110 1
b010001011001110 0
b010001011001110 .
b000000101010 &
b00000101010 (
0*
0+
b000001011010000 -
b000001011010000 '
b000001011010000 %
b000001011010000 #
08
09
b010001011010000 6
b1000 ;
b000001001010000 6
#430
0!
#435
1!
b000001001010000 $
#436
b000001011010000 /
03
04
b1000 1
b000001001010000 0
b000001001010000 .
b000000101011 &
b00000101011 (
1)
1*
b000001011010111 -
b000001011010111 '
b000001011010111 %
b000001011010111 #
17
18
b000001001010111 6
b1011 ;
b000011011010111 6
#440
0!
#445
1!
b000011011010111 $
#446
b000001011010111 /
12
13
b1011 1
b000011011010111 0
b000011011010111 .
b000000101100 &
b00000101100 (
b000001011100011 -
b000001011100011 '
b000001011100011 %
b000001011100011 #
b000011011100011 6
#450
0!
#455
1!
b000011011100011 $
#456
b000001011100011 /
b000011011100011 0
b000011011100011 .
b000000101101 &
b00000101101 (
0)
0*
b000001011100100 -
b000001011100100 '
b000001011100100 %
b000001011100100 #
07
08
b000011011100100 6
b1000 ;
b000001001100100 6
#460
0!
#465
1!
b000001001100100 $
#466
b000001011100100 /
02
03
b1000 1
b000001001100100 0
b000001001100100 .
b000000101110 &
b00000101110 (
1*
1+
b000001011111010 -
b000001011111010 '
b000001011111010 %
b000001011111010 #
18
19
b000001001111010 6
b1110 ;
b010001011111010 6
#470
0!
#475
1!
b010001011111010 $
#476
b000001011111010 /
13
14
b1110 1
b010001011111010 0
b010001011111010 .
b000000101111 &
b00000101111 (
1)
0*
b000001011111101 -
b000001011111101 '
b000001011111101 %
b000001011111101 #
17
08
b010001011111101 6
b1101 ;
b001001011111101 6
#480
0!
#485
1!
b001001011111101 $
#486
b000001011111101 /
12
03
b1101 1
b001001011111101 0
b001001011111101 .
b000000110000 &
b00000110000 (
1*
0+
0,
b000001100000011 -
b000001100000011 '
b000001100000011 %
b000001100000011 #
18
09
0:
b001001100000011 6
b0011 ;
b000001100000111 6
#490
0!
#495
1!
b000001100000111 $
#496
b000001100000011 /
13
04
05
b0011 1
b000001100000111 0
b000001100000111 .
b000000110001 &
b00000110001 (
0)
0*
b000001100000100 -
b000001100000100 '
b000001100000100 %
b000001100000100 #
07
08
b000001100000000 6
b0000 ;
b000001100000100 6
#500
0!
#505
1!
b000001100000100 $
#506
b000001100000100 /
02
03
b0000 1
b000001100000100 0
b000001100000100 .
b000000110010 &
b00000110010 (
1*
1+
b000001100011010 -
b000001100011010 '
b000001100011010 %
b000001100011010 #
18
19
b000001100011010 6
b0110 ;
b000001100111010 6
#510
0!
#515
1!
b000001100111010 $
#516
b000001100011010 /
13
14
b0110 1
b000001100111010 0
b000001100111010 .
b000000110011 &
b00000110011 (
1)
0*
b000001100011101 -
b000001100011101 '
b000001100011101 %
b000001100011101 #
17
08
b000001100111101 6
b0101 ;
b000001100001101 6
#520
0!
#525
1!
b000001100001101 $
#526
b000001100011101 /
12
03
b0101 1
b000001100001101 0
b000001100001101 .
b000000110100 &
b00000110100 (
b000001100101001 -
b000001100101001 '
b000001100101001 %
b000001100101001 #
b000001100111001 6
#530
0!
#535
1!
b000001100111001 $
#536
b000001100101001 /
b000001100111001 0
b000001100111001 .
b000000110101 &
b00000110101 (
0)
1*
b000001100101110 -
b000001100101110 '
b000001100101110 %
b000001100101110 #
07
18
b000001100111110 6
b0110 ;
b000001100001110 6
#540
0!
#545
1!
b000001100001110 $
#546
b000001100101110 /
02
13
b0110 1
b000001100001110 0
b000001100001110 .
b000000110110 &
b00000110110 (
0*
0+
b000001100110000 -
b000001100110000 '
b000001100110000 %
b000001100110000 #
08
09
b000001100010000 6
b0000 ;
b000001100110000 6
#550
0!
#555
1!
b000001100110000 $
#556
b000001100110000 /
03
04
b0000 1
b000001100110000 0
b000001100110000 .
b000000110111 &
b00000110111 (
1)
1*
b000001100110111 -
b000001100110111 '
b000001100110111 %
b000001100110111 #
17
18
b000001100110111 6
b0011 ;
b000001100110011 6
#560
0!
#565
1!
b000001100110011 $
#566
b000001100110111 /
12
13
b0011 1
b000001100110011 0
b000001100110011 .
b000000111000 &
b00000111000 (
0)
0*
1+
b000001101001000 -
b000001101001000 '
b000001101001000 %
b000001101001000 #
07
08
19
b000001101001100 6
b0100 ;
b000001101000000 6
#570
0!
#575
1!
b000001101000000 $
#576
b000001101001000 /
02
03
14
b0100 1
b000001101000000 0
b000001101000000 .
b000000111001 &
b00000111001 (
1)
1*
b000001101001111 -
b000001101001111 '
b000001101001111 %
b000001101001111 #
17
18
b000001101000111 6
b0111 ;
b000001100001111 6
#580
0!
#585
1!
b000001100001111 $
#586
b000001101001111 /
12
13
b0111 1
b000001100001111 0
b000001100001111 .
b000000111010 &
b00000111010 (
0*
0+
b000001101010001 -
b000001101010001 '
b000001101010001 %
b000001101010001 #
08
09
b000001100010001 6
b0001 ;
b000001101010000 6
#590
0!
#595
1!
b000001101010000 $
#596
b000001101010001 /
03
04
b0001 1
b000001101010000 0
b000001101010000 .
b000000111011 &
b00000111011 (
0)
1*
b000001101010110 -
b000001101010110 '
b000001101010110 %
b000001101010110 #
07
18
b000001101010111 6
b0010 ;
b000001101010100 6
#600
0!
#605
1!
b000001101010100 $
#606
b000001101010110 /
02
13
b0010 1
b000001101010100 0
b000001101010100 .
b000000111100 &
b00000111100 (
b000001101100010 -
b000001101100010 '
b000001101100010 %
b000001101100010 #
b000001101100000 6
#610
0!
#615
1!
b000001101100000 $
#616
b000001101100010 /
b000001101100000 0
b000001101100000 .
b000000111101 &
b00000111101 (
1)
0*
b000001101100101 -
b000001101100101 '
b000001101100101 %
b000001101100101 #
17
08
b000001101100111 6
b0001 ;
b000001101100100 6
#620
0!
#625
1!
b000001101100100 $
#626
b000001101100101 /
12
03
b0001 1
b000001101100100 0
b000001101100100 .
b000000111110 &
b00000111110 (
1*
1+
b000001101111011 -
b000001101111011 '
b000001101111011 %
b000001101111011 #
18
19
b000001101111010 6
b0111 ;
b000001100111011 6
#630
0!
#635
1!
b000001100111011 $
#636
b000001101111011 /
13
14
b0111 1
b000001100111011 0
b000001100111011 .
b000000111111 &
b00000111111 (
0)
0*
b000001101111100 -
b000001101111100 '
b000001101111100 %
b000001101111100 #
07
08
b000001100111100 6
b0100 ;
b000001101110100 6
#640
0!
#645
1!
b000001101110100 $
#646
b000001101111100 /
02
03
b0100 1
b000001101110100 0
b000001101110100 .
b000001000000 &
b00001000000 (
1)
1*
0+
1,
b000010010000011 -
b000010010000011 '
b000010010000011 %
b000010010000011 #
17
18
09
1:
b000010010001011 6
b1011 ;
b000000010000011 6
#650
0!
#655
1!
b000000010000011 $
#656
b000010010000011 /
12
13
04
15
b1011 1
b000000010000011 0
b000000010000011 .
b000001000001 &
b00001000001 (
0)
0*
b000010010000100 -
b000010010000100 '
b000010010000100 %
b000010010000100 #
07
08
b000000010000100 6
b1000 ;
b000010000000100 6
#660
0!
#665
1!
b000010000000100 $
#666
b000010010000100 /
02
03
b1000 1
b000010000000100 0
b000010000000100 .
b000001000010 &
b00001000010 (
1*
1+
b000010010011010 -
b000010010011010 '
b000010010011010 %
b000010010011010 #
18
19
b000010000011010 6
b1110 ;
b010010010011010 6
#670
0!
#675
1!
b010010010011010 $
#676
b000010010011010 /
13
14
b1110 1
b010010010011010 0
b010010010011010 .
b000001000011 &
b00001000011 (
1)
0*
b000010010011101 -
b000010010011101 '
b000010010011101 %
b000010010011101 #
17
08
b010010010011101 6
b1101 ;
b001010010011101 6
#680
0!
#685
1!
b001010010011101 $
#686
b000010010011101 /
12
03
b1101 1
b001010010011101 0
b001010010011101 .
b000001000100 &
b00001000100 (
b000010010101001 -
b000010010101001 '
b000010010101001 %
b000010010101001 #
b001010010101001 6
#690
0!
#695
1!
b001010010101001 $
#696
b000010010101001 /
b001010010101001 0
b001010010101001 .
b000001000101 &
b00001000101 (
0)
1*
b000010010101110 -
b000010010101110 '
b000010010101110 %
b000010010101110 #
07
18
b001010010101110 6
b1110 ;
b010010010101110 6
#700
0!
#705
1!
b010010010101110 $
#706
b000010010101110 /
02
13
b1110 1
b010010010101110 0
b010010010101110 .
b000001000110 &
b00001000110 (
0*
0+
b000010010110000 -
b000010010110000 '
b000010010110000 %
b000010010110000 #
08
09
b010010010110000 6
b1000 ;
b000010000110000 6
#710
0!
#715
1!
b000010000110000 $
#716
b000010010110000 /
03
04
b1000 1
b000010000110000 0
b000010000110000 .
b000001000111 &
b00001000111 (
1)
1*
b000010010110111 -
b000010010110111 '
b000010010110111 %
b000010010110111 #
17
18
b000010000110111 6
b1011 ;
b000000010110111 6
#720
0!
#725
1!
b000000010110111 $
#726
b000010010110111 /
12
13
b1011 1
b000000010110111 0
b000000010110111 .
b000001001000 &
b00001001000 (
0)
0*
1+
b000010011001000 -
b000010011001000 '
b000010011001000 %
b000010011001000 #
07
08
19
b000000011001000 6
b1100 ;
b000110011001000 6
#730
0!
#735
1!
b000110011001000 $
#736
b000010011001000 /
02
03
14
b1100 1
b000110011001000 0
b000110011001000 .
b000001001001 &
b00001001001 (
1)
1*
b000010011001111 -
b000010011001111 '
b000010011001111 %
b000010011001111 #
17
18
b000110011001111 6
b1111 ;
b100010011001111 6
#740
0!
#745
1!
b100010011001111 $
#746
b000010011001111 /
12
13
b1111 1
b100010011001111 0
b100010011001111 .
b000001001010 &
b00001001010 (
0*
0+
b000010011010001 -
b000010011010001 '
b000010011010001 %
b000010011010001 #
08
09
b100010011010001 6
b1001 ;
b000010111010001 6
#750
0!
#755
1!
b000010111010001 $
#756
b000010011010001 /
03
04
b1001 1
b000010111010001 0
b000010111010001 .
b000001001011 &
b00001001011 (
0)
1*
b000010011010110 -
b000010011010110 '
b000010011010110 %
b000010011010110 #
07
18
b000010111010110 6
b1010 ;
b000011011010110 6
#760
0!
#765
1!
b000011011010110 $
#766
b000010011010110 /
02
13
b1010 1
b000011011010110 0
b000011011010110 .
b000001001100 &
b00001001100 (
b000010011100010 -
b000010011100010 '
b000010011100010 %
b000010011100010 #
b000011011100010 6
#770
0!
#775
1!
b000011011100010 $
#776
b000010011100010 /
b000011011100010 0
b000011011100010 .
b000001001101 &
b00001001101 (
1)
0*
b000010011100101 -
b000010011100101 '
b000010011100101 %
b000010011100101 #
17
08
b000011011100101 6
b1001 ;
b000010111100101 6
#780
0!
#785
1!
b000010111100101 $
#786
b000010011100101 /
12
03
b1001 1
b000010111100101 0
b000010111100101 .
b000001001110 &
b00001001110 (
1*
1+
b000010011111011 -
b000010011111011 '
b000010011111011 %
b000010011111011 #
18
19
b000010111111011 6
b1111 ;
b100010011111011 6
#790
0!
#795
1!
b100010011111011 $
#796
b000010011111011 /
13
14
b1111 1
b100010011111011 0
b100010011111011 .
b000001001111 &
b00001001111 (
0)
0*
b000010011111100 -
b000010011111100 '
b000010011111100 %
b000010011111100 #
07
08
b100010011111100 6
b1100 ;
b000110011111100 6
#800
0!
#805
1!
b000110011111100 $
#806
b000010011111100 /
02
03
b1100 1
b000110011111100 0
b000110011111100 .
b000001010000 &
b00001010000 (
1*
0+
0,
b000010100000010 -
b000010100000010 '
b000010100000010 %
b000010100000010 #
18
09
0:
b000110100000010 6
b0010 ;
b000010100000000 6
#810
0!
#815
1!
b000010100000000 $
#816
b000010100000010 /
13
04
05
b0010 1
b000010100000000 0
b000010100000000 .
b000001010001 &
b00001010001 (
1)
0*
b000010100000101 -
b000010100000101 '
b000010100000101 %
b000010100000101 #
17
08
b000010100000111 6
b0001 ;
b000010100000100 6
#820
0!
#825
1!
b000010100000100 $
#826
b000010100000101 /
12
03
b0001 1
b000010100000100 0
b000010100000100 .
b000001010010 &
b00001010010 (
1*
1+
b000010100011011 -
b000010100011011 '
b000010100011011 %
b000010100011011 #
18
19
b000010100011010 6
b0111 ;
b000010101011011 6
#830
0!
#835
1!
b000010101011011 $
#836
b000010100011011 /
13
14
b0111 1
b000010101011011 0
b000010101011011 .
b000001010011 &
b00001010011 (
0)
0*
b000010100011100 -
b000010100011100 '
b000010100011100 %
b000010100011100 #
07
08
b000010101011100 6
b0100 ;
b000010100010100 6
#840
0!
#845
1!
b000010100010100 $
#846
b000010100011100 /
02
03
b0100 1
b000010100010100 0
b000010100010100 .
b000001010100 &
b00001010100 (
b000010100101000 -
b000010100101000 '
b000010100101000 %
b000010100101000 #
b000010100100000 6
#850
0!
#855
1!
b000010100100000 $
#856
b000010100101000 /
b000010100100000 0
b000010100100000 .
b000001010101 &
b00001010101 (
1)
1*
b000010100101111 -
b000010100101111 '
b000010100101111 %
b000010100101111 #
17
18
b000010100100111 6
b0111 ;
b000010101101111 6
#860
0!
